LICENSE
MANIFEST.in
README.md
SpliceURL.py
setup.py
SpliceURL.egg-info/PKG-INFO
SpliceURL.egg-info/SOURCES.txt
SpliceURL.egg-info/dependency_links.txt
SpliceURL.egg-info/top_level.txt